{"frames":{"walk_0":{"frame":{"x":774,"y":0,"w":181,"h":314},"rotated":false,"trimmed":true,"spriteSourceSize":{"x":109,"y":67,"w":181,"h":314},"sourceSize":{"w":399,"h":399}},"walk_1":{"frame":{"x":555,"y":338,"w":112,"h":300},"rotated":false,"trimmed":true,"spriteSourceSize":{"x":144,"y":81,"w":112,"h":300},"sourceSize":{"w":399,"h":399}},"walk_2":{"frame":{"x":0,"y":338,"w":181,"h":314},"rotated":false,"trimmed":true,"spriteSourceSize":{"x":109,"y":67,"w":181,"h":314},"sourceSize":{"w":399,"h":399}},"walk_3":{"frame":{"x":436,"y":338,"w":117,"h":307},"rotated":false,"trimmed":true,"spriteSourceSize":{"x":141,"y":74,"w":117,"h":307},"sourceSize":{"w":399,"h":399}},"attack_0":{"frame":{"x":587,"y":0,"w":185,"h":324},"rotated":false,"trimmed":true,"spriteSourceSize":{"x":107,"y":57,"w":185,"h":324},"sourceSize":{"w":399,"h":399}},"attack_1":{"frame":{"x":669,"y":338,"w":259,"h":296},"rotated":false,"trimmed":true,"spriteSourceSize":{"x":70,"y":85,"w":259,"h":296},"sourceSize":{"w":399,"h":399}},"attack_2":{"frame":{"x":0,"y":0,"w":138,"h":336},"rotated":false,"trimmed":true,"spriteSourceSize":{"x":131,"y":45,"w":138,"h":336},"sourceSize":{"w":399,"h":399}},"hit_0":{"frame":{"x":140,"y":0,"w":245,"h":336},"rotated":false,"trimmed":true,"spriteSourceSize":{"x":77,"y":45,"w":245,"h":336},"sourceSize":{"w":399,"h":399}},"hit_1":{"frame":{"x":387,"y":0,"w":198,"h":335},"rotated":false,"trimmed":true,"spriteSourceSize":{"x":101,"y":46,"w":198,"h":335},"sourceSize":{"w":399,"h":399}},"death_0":{"frame":{"x":183,"y":338,"w":251,"h":313},"rotated":false,"trimmed":true,"spriteSourceSize":{"x":74,"y":68,"w":251,"h":313},"sourceSize":{"w":399,"h":399}},"death_1":{"frame":{"x":0,"y":654,"w":245,"h":260},"rotated":false,"trimmed":true,"spriteSourceSize":{"x":77,"y":121,"w":245,"h":260},"sourceSize":{"w":399,"h":399}},"death_2":{"frame":{"x":247,"y":654,"w":279,"h":247},"rotated":false,"trimmed":true,"spriteSourceSize":{"x":60,"y":134,"w":279,"h":247},"sourceSize":{"w":399,"h":399}}},"meta":{"app":"pack-anim-atlas.mjs","image":"scrapper_stage_01.webp","scale":"1","size":{"w":955,"h":914}}}